pocket_protector/__init__.py
pocket_protector/__main__.py
pocket_protector/_version.py
pocket_protector/cli.py
pocket_protector/file_keys.py
pocket_protector/tests/__init__.py
pocket_protector/tests/conftest.py
pocket_protector/tests/test_cli.py
pocket_protector/tests/test_file_keys.py
pocket_protector-20.0.1.dist-info/LICENSE.txt
pocket_protector-20.0.1.dist-info/METADATA
pocket_protector-20.0.1.dist-info/WHEEL
pocket_protector-20.0.1.dist-info/entry_points.txt
pocket_protector-20.0.1.dist-info/top_level.txt
pocket_protector-20.0.1.dist-info/RECORD
