Metadata-Version: 2.1
Name: pocket-protector
Version: 20.0.1
Summary: Handy secret management system with a convenient CLI and readable storage format.
Home-page: https://github.com/SimpleLegal/pocket_protector
Author: Kurt Rose and Mahmoud Hashemi
Author-email: kurt@kurtrose.com
License: Apache License 2.0
Platform: any
Requires-Dist: attrs
Requires-Dist: boltons
Requires-Dist: PyNaCl
Requires-Dist: ruamel.yaml
Requires-Dist: schema
Requires-Dist: face (>=20.1.1)
